{
	"info": {
		"_postman_id": "e31c30db-b6c2-4c21-9643-3a9bb2ecc834",
		"name": "MyMonit",
		"schema": "https://schema.getpostman.com/json/collection/v2.1.0/collection.json"
	},
	"item": [
		{
			"name": "users",
			"item": [
				{
					"name": "create users",
					"protocolProfileBehavior": {
						"disabledSystemHeaders": {
							"content-type": true
						}
					},
					"request": {
						"method": "POST",
						"header": [
							{
								"key": "Content-Type",
								"value": "application/json",
								"type": "default"
							}
						],
						"body": {
							"mode": "raw",
							"raw": "{\n    \"user_id\": \"S010\",\n    \"name\": \"Foo Bar\",\n    \"username\": \"foo\",\n    \"email\": \"foo@bar.com\",\n    \"role\": \"SCIENTIST\"\n}"
						},
						"url": {
							"raw": "{{url}}/users",
							"host": [
								"{{url}}"
							],
							"path": [
								"users"
							]
						}
					},
					"response": []
				},
				{
					"name": "retrieve users",
					"protocolProfileBehavior": {
						"disableBodyPruning": true,
						"disabledSystemHeaders": {
							"content-type": true
						}
					},
					"request": {
						"method": "GET",
						"header": [
							{
								"key": "Content-Type",
								"value": "application/json",
								"type": "default"
							}
						],
						"body": {
							"mode": "raw",
							"raw": ""
						},
						"url": {
							"raw": "{{url}}/experiments",
							"host": [
								"{{url}}"
							],
							"path": [
								"experiments"
							]
						}
					},
					"response": []
				}
			]
		},
		{
			"name": "experiments",
			"item": [
				{
					"name": "retrieve experiment",
					"protocolProfileBehavior": {
						"disableBodyPruning": true,
						"disabledSystemHeaders": {
							"content-type": true
						}
					},
					"request": {
						"method": "GET",
						"header": [
							{
								"key": "Content-Type",
								"value": "application/json",
								"type": "default"
							}
						],
						"body": {
							"mode": "raw",
							"raw": ""
						},
						"url": {
							"raw": "{{url}}/experiments",
							"host": [
								"{{url}}"
							],
							"path": [
								"experiments"
							]
						}
					},
					"response": []
				},
				{
					"name": "create experiment",
					"protocolProfileBehavior": {
						"disabledSystemHeaders": {
							"content-type": true
						}
					},
					"request": {
						"method": "POST",
						"header": [
							{
								"key": "Content-Type",
								"value": "application/json",
								"type": "default"
							}
						],
						"body": {
							"mode": "raw",
							"raw": "{\n    \"name\": \"EXP0001\"\n}"
						},
						"url": {
							"raw": "{{url}}/experiments",
							"host": [
								"{{url}}"
							],
							"path": [
								"experiments"
							]
						}
					},
					"response": []
				}
			]
		},
		{
			"name": "measures",
			"item": [
				{
					"name": "retrieve measures",
					"request": {
						"method": "GET",
						"header": [],
						"url": {
							"raw": "{{url}}/measures/1",
							"host": [
								"{{url}}"
							],
							"path": [
								"measures",
								"1"
							]
						}
					},
					"response": []
				}
			]
		},
		{
			"name": "authentication",
			"item": [
				{
					"name": "authenticate",
					"request": {
						"auth": {
							"type": "noauth"
						},
						"method": "POST",
						"header": [
							{
								"key": "Content-Type",
								"value": "application/json",
								"type": "default"
							}
						],
						"body": {
							"mode": "raw",
							"raw": "{\"username\":\"S001\"}"
						},
						"url": {
							"raw": "{{url}}/authenticate",
							"host": [
								"{{url}}"
							],
							"path": [
								"authenticate"
							]
						}
					},
					"response": []
				}
			]
		}
	],
	"auth": {
		"type": "bearer",
		"bearer": [
			{
				"key": "token",
				"value": "{{token}}",
				"type": "string"
			}
		]
	},
	"event": [
		{
			"listen": "prerequest",
			"script": {
				"type": "text/javascript",
				"exec": [
					""
				]
			}
		},
		{
			"listen": "test",
			"script": {
				"type": "text/javascript",
				"exec": [
					""
				]
			}
		}
	]
}